{
	"titles": ["1st round", "Quarter", "Semi", "Finale"],
	"rounds": [
		[
			{
				"player1": {
					"name": "GRAMMATIK./TIKHONOVA"
				},
				"player2": {
					"name": "Bye"
				}
			},
			{
				"player1": {
					"name": "ANANE/GENOVESE"
				},
				"player2": {
					"name": "BELGRAVER/MANSOURI"
				}
			},
			{
				"player1": {
					"name": "HERAZO./PEREZ."
				},
				"player2": {
					"name": "Bye"
				}
			},
			{
				"player1": {
					"name": "HATOUKA/ROSCA"
				},
				"player2": {
					"name": "RAKOTOMANGA./STAMATOVA"
				}
			},
			{
				"player1": {
					"name": "ALBIE/KEMPEN"
				},
				"player2": {
					"name": "BURRAGE/SEWING"
				}
			},
			{
				"player1": {
					"name": "Bye"
				},
				"player2": {
					"name": "CONTRERAS./SUN"
				}
			},
			{
				"player1": {
					"name": "SAIGO/SAIGO"
				},
				"player2": {
					"name": "DARTRON/SZOSTAK"
				}
			},
			{
				"player1": {
					"name": "Bye"
				},
				"player2": {
					"name": "NAGY/THOMBARE"
				}
			}
		],
		[
            {
				"player1": {
					"name": "GRAMMATIK./TIKHONOVA"
				},
				"player2": {
					"name": "BELGRAVER/MANSOURI",
                    "score": "6/2 2/6 10/6"
				}
			},
            {
				"player1": {
					"name": "HERAZO./PEREZ."
				},
				"player2": {
					"name": ""
				}
			},
            {
				"player1": {
					"name": "ALBIE/KEMPEN",
                    "score": "6/2 7/6 (5)"
				},
				"player2": {
					"name": "CONTRERAS./SUN"
				}
			},
            {
				"player1": {
					"name": "DARTRON/SZOSTAK",
                    "score": "7/5 4/6 10/6"
				},
				"player2": {
					"name": "NAGY/THOMBARE"
				}
			}
        ],
		[ ],
		[ ],
		[ ]
	]
}